pppca/core.py
pppca-0.0.1.dist-info/METADATA
pppca-0.0.1.dist-info/WHEEL
pppca-0.0.1.dist-info/licenses/LICENSE
pppca-0.0.1.dist-info/RECORD
