Metadata-Version: 2.4
Name: pppca
Version: 0.0.1
Summary: PCA for multivariate point processes
Project-URL: Homepage, https://github.com/kharoh/pppca
Project-URL: Repository, https://github.com/kharoh/pppca
Project-URL: Issues, https://github.com/kharoh/pppca/issues
Author-email: Kharoh <gaulu03@gmail.com>
License-Expression: Apache-2.0
License-File: LICENSE
Keywords: functional-data-analysis,pca,point-processes,pytorch,statistics
Classifier: Development Status :: 3 - Alpha
Classifier: Intended Audience :: Science/Research
Classifier: License :: OSI Approved :: Apache Software License
Classifier: Programming Language :: Python :: 3
Classifier: Programming Language :: Python :: 3.9
Classifier: Programming Language :: Python :: 3.10
Classifier: Programming Language :: Python :: 3.11
Classifier: Topic :: Scientific/Engineering :: Artificial Intelligence
Classifier: Topic :: Scientific/Engineering :: Mathematics
Requires-Python: >=3.9
Requires-Dist: numpy>=1.20
Requires-Dist: pandas>=1.3
Requires-Dist: torch>=2.0
Requires-Dist: tqdm>=4.60
Provides-Extra: dev
Requires-Dist: matplotlib>=3.5; extra == 'dev'
Requires-Dist: mypy>=1.0; extra == 'dev'
Requires-Dist: pytest-cov>=4.0; extra == 'dev'
Requires-Dist: pytest>=7.0; extra == 'dev'
Requires-Dist: ruff>=0.1; extra == 'dev'
